nexus_sdk/__init__.py
nexus_sdk/api_client.py
nexus_sdk/apis/__init__.py
nexus_sdk/apis/path_to_api.py
nexus_sdk/apis/paths/__init__.py
nexus_sdk/apis/paths/beta_replication_connection.py
nexus_sdk/apis/paths/beta_replication_connection_name.py
nexus_sdk/apis/paths/beta_replicationtarget_repository_enable.py
nexus_sdk/apis/paths/beta_replicationtarget_repository_repository_name_enable.py
nexus_sdk/apis/paths/v1_assets.py
nexus_sdk/apis/paths/v1_assets_id.py
nexus_sdk/apis/paths/v1_azureblobstore_test_connection.py
nexus_sdk/apis/paths/v1_blobstores.py
nexus_sdk/apis/paths/v1_blobstores_azure.py
nexus_sdk/apis/paths/v1_blobstores_azure_name.py
nexus_sdk/apis/paths/v1_blobstores_file.py
nexus_sdk/apis/paths/v1_blobstores_file_name.py
nexus_sdk/apis/paths/v1_blobstores_group.py
nexus_sdk/apis/paths/v1_blobstores_group_convert_name_new_name_for_original.py
nexus_sdk/apis/paths/v1_blobstores_group_name.py
nexus_sdk/apis/paths/v1_blobstores_name.py
nexus_sdk/apis/paths/v1_blobstores_name_quota_status.py
nexus_sdk/apis/paths/v1_blobstores_s3.py
nexus_sdk/apis/paths/v1_blobstores_s3_name.py
nexus_sdk/apis/paths/v1_components.py
nexus_sdk/apis/paths/v1_components_id.py
nexus_sdk/apis/paths/v1_email.py
nexus_sdk/apis/paths/v1_email_verify.py
nexus_sdk/apis/paths/v1_formats_format_upload_specs.py
nexus_sdk/apis/paths/v1_formats_upload_specs.py
nexus_sdk/apis/paths/v1_iq.py
nexus_sdk/apis/paths/v1_iq_disable.py
nexus_sdk/apis/paths/v1_iq_enable.py
nexus_sdk/apis/paths/v1_iq_verify_connection.py
nexus_sdk/apis/paths/v1_lifecycle_bounce.py
nexus_sdk/apis/paths/v1_lifecycle_phase.py
nexus_sdk/apis/paths/v1_read_only.py
nexus_sdk/apis/paths/v1_read_only_force_release.py
nexus_sdk/apis/paths/v1_read_only_freeze.py
nexus_sdk/apis/paths/v1_read_only_release.py
nexus_sdk/apis/paths/v1_repositories.py
nexus_sdk/apis/paths/v1_repositories_apt_hosted.py
nexus_sdk/apis/paths/v1_repositories_apt_hosted_repository_name.py
nexus_sdk/apis/paths/v1_repositories_apt_proxy.py
sonatype_nexus_sdk-0.1.3.dist-info/METADATA
sonatype_nexus_sdk-0.1.3.dist-info/WHEEL
sonatype_nexus_sdk-0.1.3.dist-info/RECORD
