Metadata-Version: 2.1
Name: sonatype-nexus-sdk
Version: 0.1.3
Summary: Python SDK for Sonatype Products such as Nexus Repository Manager, Lifecycle and IQ Server 
License: MIT
Author: Justin Bailey
Author-email: justthered63@gmail.com
Requires-Python: >=3.9,<4.0
Classifier: License :: OSI Approved :: MIT License
Classifier: Programming Language :: Python :: 3
Classifier: Programming Language :: Python :: 3.9
Classifier: Programming Language :: Python :: 3.10
Classifier: Programming Language :: Python :: 3.11
Requires-Dist: certifi (>=2023.5.7,<2024.0.0)
Requires-Dist: frozendict (>=2.3.8,<3.0.0)
Requires-Dist: python-dateutil (>=2.8.2,<3.0.0)
Requires-Dist: setuptools (>=67.8.0,<68.0.0)
Requires-Dist: typing-extensions (>=4.6.2,<5.0.0)
Requires-Dist: urllib3 (>=2.0.2,<3.0.0)
